{
	"info": {
		"_postman_id": "e507a69f-c09d-4e9b-a3ff-05c0a1fd3c8a",
		"name": "News API Postman collection",
		"schema": "https://schema.getpostman.com/json/collection/v2.1.0/collection.json",
		"_exporter_id": "9499370",
		"_collection_link": "https://www.postman.com/cloudy-comet-97263/workspace/inns-backed-2024/collection/9499370-e507a69f-c09d-4e9b-a3ff-05c0a1fd3c8a?action=share&source=collection_link&creator=9499370"
	},
	"item": [
		{
			"name": "News",
			"item": [
				{
					"name": "Get news",
					"protocolProfileBehavior": {
						"disabledSystemHeaders": {
							"accept": true
						}
					},
					"request": {
						"auth": {
							"type": "bearer",
							"bearer": [
								{
									"key": "token",
									"value": "{{authToken}}",
									"type": "string"
								}
							]
						},
						"method": "GET",
						"header": [
							{
								"key": "Accept",
								"value": "application/json",
								"type": "text"
							}
						],
						"url": {
							"raw": "{{base_url}}/news/search?source=nyt&keyword=it&fromDate=2024-01-24&toDate=2024-12-24&page=2",
							"host": [
								"{{base_url}}"
							],
							"path": [
								"news",
								"search"
							],
							"query": [
								{
									"key": "source",
									"value": "nyt"
								},
								{
									"key": "keyword",
									"value": "it"
								},
								{
									"key": "fromDate",
									"value": "2024-01-24"
								},
								{
									"key": "toDate",
									"value": "2024-12-24"
								},
								{
									"key": "page",
									"value": "2"
								}
							]
						}
					},
					"response": []
				}
			]
		},
		{
			"name": "Auth",
			"item": [
				{
					"name": "Login",
					"request": {
						"method": "POST",
						"header": [],
						"body": {
							"mode": "formdata",
							"formdata": [
								{
									"key": "email",
									"value": "prem@gmail.comaa",
									"type": "text"
								},
								{
									"key": "password",
									"value": "12345678",
									"type": "text"
								}
							]
						},
						"url": {
							"raw": "{{base_url}}/auth/login",
							"host": [
								"{{base_url}}"
							],
							"path": [
								"auth",
								"login"
							]
						}
					},
					"response": []
				},
				{
					"name": "Register",
					"request": {
						"method": "POST",
						"header": [],
						"body": {
							"mode": "formdata",
							"formdata": [
								{
									"key": "name",
									"value": "lala",
									"type": "text"
								},
								{
									"key": "email",
									"value": "prem@gmail.coma1a",
									"type": "text"
								},
								{
									"key": "password",
									"value": "12345678",
									"type": "text"
								},
								{
									"key": "password_confirmation",
									"value": "12345678",
									"type": "text"
								}
							]
						},
						"url": {
							"raw": "{{base_url}}/auth/register",
							"host": [
								"{{base_url}}"
							],
							"path": [
								"auth",
								"register"
							]
						}
					},
					"response": []
				},
				{
					"name": "Logout",
					"protocolProfileBehavior": {
						"disabledSystemHeaders": {
							"accept": true
						}
					},
					"request": {
						"auth": {
							"type": "bearer",
							"bearer": [
								{
									"key": "token",
									"value": "{{authToken}}",
									"type": "string"
								}
							]
						},
						"method": "POST",
						"header": [
							{
								"key": "Accept",
								"value": "application/json",
								"type": "text"
							}
						],
						"url": {
							"raw": "{{base_url}}/auth/logout",
							"host": [
								"{{base_url}}"
							],
							"path": [
								"auth",
								"logout"
							]
						}
					},
					"response": []
				}
			]
		},
		{
			"name": "User Preference",
			"item": [
				{
					"name": "Save or update",
					"protocolProfileBehavior": {
						"disabledSystemHeaders": {
							"accept": true
						}
					},
					"request": {
						"auth": {
							"type": "bearer",
							"bearer": [
								{
									"key": "token",
									"value": "{{authToken}}",
									"type": "string"
								}
							]
						},
						"method": "POST",
						"header": [
							{
								"key": "Accept",
								"value": "application/json",
								"type": "text"
							}
						],
						"body": {
							"mode": "formdata",
							"formdata": [
								{
									"key": "source",
									"value": "tesla",
									"type": "text"
								},
								{
									"key": "category",
									"value": "df",
									"type": "text"
								}
							]
						},
						"url": {
							"raw": "{{base_url}}/user/preference",
							"host": [
								"{{base_url}}"
							],
							"path": [
								"user",
								"preference"
							]
						}
					},
					"response": []
				},
				{
					"name": "Get",
					"protocolProfileBehavior": {
						"disableBodyPruning": true,
						"disabledSystemHeaders": {
							"accept": true
						}
					},
					"request": {
						"auth": {
							"type": "bearer",
							"bearer": [
								{
									"key": "token",
									"value": "{{authToken}}",
									"type": "string"
								}
							]
						},
						"method": "GET",
						"header": [
							{
								"key": "Accept",
								"value": "application/json",
								"type": "text"
							}
						],
						"body": {
							"mode": "formdata",
							"formdata": []
						},
						"url": {
							"raw": "{{base_url}}/user/preference",
							"host": [
								"{{base_url}}"
							],
							"path": [
								"user",
								"preference"
							]
						}
					},
					"response": []
				}
			]
		}
	],
	"event": [
		{
			"listen": "prerequest",
			"script": {
				"type": "text/javascript",
				"packages": {},
				"exec": [
					""
				]
			}
		},
		{
			"listen": "test",
			"script": {
				"type": "text/javascript",
				"packages": {},
				"exec": [
					""
				]
			}
		}
	],
	"variable": [
		{
			"key": "base_url",
			"value": "http://127.0.0.1:8000/api\n",
			"type": "string"
		},
		{
			"key": "authToken",
			"value": "",
			"type": "string"
		}
	]
}